vtpk_reader/__init__.py
vtpk_reader/vtpk_reader.py
vtpk_reader-0.1.0.dist-info/LICENSE
vtpk_reader-0.1.0.dist-info/METADATA
vtpk_reader-0.1.0.dist-info/WHEEL
vtpk_reader-0.1.0.dist-info/RECORD
