Metadata-Version: 2.3
Name: vtpk-reader
Version: 0.1.0
Summary: Reading ESRI Vector Tile Package (vtpk) files.
License: MIT
Author: Kirill Shklovsky
Author-email: kirill.shklovsky@gmail.com
Requires-Python: >=3.9,<4.0
Classifier: License :: OSI Approved :: MIT License
Classifier: Programming Language :: Python :: 3
Classifier: Programming Language :: Python :: 3.9
Classifier: Programming Language :: Python :: 3.10
Classifier: Programming Language :: Python :: 3.11
Classifier: Programming Language :: Python :: 3.12
Classifier: Programming Language :: Python :: 3.13
Requires-Dist: mapbox-vector-tile (>=2.1.0,<3.0.0)
Requires-Dist: pyproj (>=3.4.1,<4.0.0)
Requires-Dist: shapely (>=2.0.0,<3.0.0)
Project-URL: Repository, https://github.com/kshklovsky/vtpk-reader
